django_react_tailwind_vite/__init__.py
django_react_tailwind_vite/setup_project.py
django_react_tailwind_vite/constants/__init__.py
django_react_tailwind_vite/constants/names.py
django_react_tailwind_vite/content/__init__.py
django_react_tailwind_vite/content/components.py
django_react_tailwind_vite/content/environments.py
django_react_tailwind_vite/content/gitinore.py
django_react_tailwind_vite/content/helpers_dir.py
django_react_tailwind_vite/content/hooks.py
django_react_tailwind_vite/content/html.py
django_react_tailwind_vite/content/package_json.py
django_react_tailwind_vite/content/redux_actions.py
django_react_tailwind_vite/content/redux_middleware.py
django_react_tailwind_vite/content/redux_reducer.py
django_react_tailwind_vite/content/redux_store.py
django_react_tailwind_vite/content/requirements.py
django_react_tailwind_vite/content/src_dir.py
django_react_tailwind_vite/content/static_dir.py
django_react_tailwind_vite/content/ts_config.py
django_react_tailwind_vite/content/vite_config.py
django_react_tailwind_vite/content/dwango/__init__.py
django_react_tailwind_vite/content/dwango/asgi.py
django_react_tailwind_vite/content/dwango/manage.py
django_react_tailwind_vite/content/dwango/settings.py
django_react_tailwind_vite/content/dwango/urls.py
django_react_tailwind_vite/content/dwango/wsgi.py
django_react_tailwind_vite/utils/__init__.py
django_react_tailwind_vite/utils/setup_django_dir.py
django_react_tailwind_vite/utils/setup_frontend_dir.py
django_react_tailwind_vite/utils/setup_root_dir.py
django_react_tailwind_vite-0.1.7.dist-info/METADATA
django_react_tailwind_vite-0.1.7.dist-info/WHEEL
django_react_tailwind_vite-0.1.7.dist-info/entry_points.txt
django_react_tailwind_vite-0.1.7.dist-info/licenses/LICENSE
django_react_tailwind_vite-0.1.7.dist-info/RECORD
