Metadata-Version: 2.4
Name: django-react-tailwind-vite
Version: 0.1.7
Summary: Script to set up a Django-React hybrid project with Tailwind CSS and Vite
Project-URL: repository, https://github.com/AsinineFatuity/django-react-tailwind-vite
Project-URL: homepage, https://github.com/AsinineFatuity/django-react-tailwind-vite
Project-URL: documentation, https://github.com/AsinineFatuity/django-react-tailwind-vite
Author-email: Kembo Franklyne <kembofranklyne@gmail.com>
License: MIT
License-File: LICENSE
Requires-Python: >=3.10
